optimizely/__init__.py
optimizely/client.py
optimizely/core/__init__.py
optimizely/core/api_error.py
optimizely/core/client_wrapper.py
optimizely/core/datetime_utils.py
optimizely/core/jsonable_encoder.py
optimizely/core/remove_none_from_dict.py
optimizely/errors/__init__.py
optimizely/errors/unprocessable_entity_error.py
optimizely/py.typed
optimizely/resources/__init__.py
optimizely/resources/models/__init__.py
optimizely/resources/models/client.py
optimizely/resources/proxy/__init__.py
optimizely/resources/proxy/client.py
optimizely/types/__init__.py
optimizely/types/chat_completions_response_dto.py
optimizely/types/chat_completions_usage_dto.py
optimizely/types/chat_message_dto.py
optimizely/types/chat_request_dto.py
optimizely/types/http_validation_error.py
optimizely/types/model_dto.py
optimizely/types/models_response_dto.py
optimizely/types/tokens_response_dto.py
optimizely/types/validation_error.py
optimizely/types/validation_error_loc_item.py
fern_optimizely-0.0.11.dist-info/METADATA
fern_optimizely-0.0.11.dist-info/WHEEL
fern_optimizely-0.0.11.dist-info/RECORD
